<?xml version='1.0' encoding='UTF-8'?>
<faces-config version="2.2"
              xmlns="http://xmlns.jcp.org/xml/ns/javaee"
              xmlns:xsi="http://www.w3.org/2001/XMLSchema-instance"
              xsi:schemaLocation="http://xmlns.jcp.org/xml/ns/javaee http://xmlns.jcp.org/xml/ns/javaee/web-facesconfig_2_2.xsd">
    <managed-bean>
        <managed-bean-name>usuarioBean</managed-bean-name>
        <managed-bean-class>com.planit.smsrenta.controladores.UsuarioBean</managed-bean-class>        
        <managed-bean-scope>session</managed-bean-scope>
    </managed-bean>
    <managed-bean>
        <managed-bean-name>marcaBean</managed-bean-name>
        <managed-bean-class>com.planit.smsrenta.controladores.MarcaBean</managed-bean-class>    
        <managed-bean-scope>view</managed-bean-scope>
    </managed-bean>
    <managed-bean>
        <managed-bean-name>contratoBean</managed-bean-name>
        <managed-bean-class>com.planit.smsrenta.controladores.ContratoBean</managed-bean-class>
        <managed-bean-scope>view</managed-bean-scope>
    </managed-bean>
    <managed-bean>
        <managed-bean-name>costosServicioBean</managed-bean-name>
        <managed-bean-class>com.planit.smsrenta.controladores.CostosServicioBean</managed-bean-class>    
        <managed-bean-scope>view</managed-bean-scope>
    </managed-bean>
    <managed-bean>
        <managed-bean-name>clienteBean</managed-bean-name>
        <managed-bean-class>com.planit.smsrenta.controladores.ClienteBean</managed-bean-class>    
        <managed-bean-scope>view</managed-bean-scope>
    </managed-bean>
    <managed-bean>
        <managed-bean-name>proveedorBean</managed-bean-name>
        <managed-bean-class>com.planit.smsrenta.controladores.ProveedorBean</managed-bean-class>    
        <managed-bean-scope>view</managed-bean-scope>
    </managed-bean>
    <managed-bean>
        <managed-bean-name>empleadoBean</managed-bean-name>
        <managed-bean-class>com.planit.smsrenta.controladores.EmpleadoBean</managed-bean-class>    
        <managed-bean-scope>view</managed-bean-scope>
    </managed-bean>
    <managed-bean>
        <managed-bean-name>rolBean</managed-bean-name>
        <managed-bean-class>com.planit.smsrenta.controladores.RolBean</managed-bean-class>        
        <managed-bean-scope>view</managed-bean-scope>
    </managed-bean>
    <managed-bean>
        <managed-bean-name>permisosBean</managed-bean-name>
        <managed-bean-class>com.planit.smsrenta.controladores.PermisosBean</managed-bean-class>    
        <managed-bean-scope>view</managed-bean-scope>
    </managed-bean>
    <managed-bean>
        <managed-bean-name>ciudadBean</managed-bean-name>
        <managed-bean-class>com.planit.smsrenta.controladores.CiudadBean</managed-bean-class>        
        <managed-bean-scope>view</managed-bean-scope>
    </managed-bean>
    <managed-bean>
        <managed-bean-name>vehiculoBean</managed-bean-name>
        <managed-bean-class>com.planit.smsrenta.controladores.VehiculoBean</managed-bean-class>        
        <managed-bean-scope>view</managed-bean-scope>
    </managed-bean>
    <managed-bean>
        <managed-bean-name>referenciaBean</managed-bean-name>
        <managed-bean-class>com.planit.smsrenta.controladores.ReferenciaBean</managed-bean-class>        
        <managed-bean-scope>view</managed-bean-scope>
    </managed-bean>
    <managed-bean>
        <managed-bean-name>categoriaBean</managed-bean-name>
        <managed-bean-class>com.planit.smsrenta.controladores.CategoriaBean</managed-bean-class>        
        <managed-bean-scope>view</managed-bean-scope>
    </managed-bean>
    <managed-bean>
        <managed-bean-name>calificacionBean</managed-bean-name>
        <managed-bean-class>com.planit.smsrenta.controladores.CalificacionBean</managed-bean-class>        
        <managed-bean-scope>session</managed-bean-scope>
    </managed-bean>
    <managed-bean>
        <managed-bean-name>reservacionBean</managed-bean-name>
        <managed-bean-class>com.planit.smsrenta.controladores.ReservacionBean</managed-bean-class>        
        <managed-bean-scope>session</managed-bean-scope>
    </managed-bean>
    <managed-bean>
        <managed-bean-name>serviciosBean</managed-bean-name>
        <managed-bean-class>com.planit.smsrenta.controladores.ServiciosBean</managed-bean-class>        
        <managed-bean-scope>view</managed-bean-scope>
    </managed-bean>
    <managed-bean>
        <managed-bean-name>paisBean</managed-bean-name>
        <managed-bean-class>com.planit.smsrenta.controladores.PaisBean</managed-bean-class>        
        <managed-bean-scope>view</managed-bean-scope>
    </managed-bean>
    <managed-bean>
        <managed-bean-name>pruebaBean</managed-bean-name>
        <managed-bean-class>com.planit.smsrenta.controladores.PruebaBean</managed-bean-class>        
        <managed-bean-scope>view</managed-bean-scope>
    </managed-bean>
    <managed-bean>
        <managed-bean-name>pathBean</managed-bean-name>
        <managed-bean-class>com.planit.smsrenta.controladores.PathBean</managed-bean-class>        
        <managed-bean-scope>view</managed-bean-scope>
    </managed-bean>
    <managed-bean>
        <managed-bean-name>carouselBean</managed-bean-name>
        <managed-bean-class>com.planit.smsrenta.controladores.carouselBean</managed-bean-class>        
        <managed-bean-scope>view</managed-bean-scope>
    </managed-bean>
    <managed-bean>
        <managed-bean-name>lugarBean</managed-bean-name>
        <managed-bean-class>com.planit.smsrenta.controladores.LugarBean</managed-bean-class>        
        <managed-bean-scope>view</managed-bean-scope>
    </managed-bean>
    <managed-bean>
        <managed-bean-name>administradorBean</managed-bean-name>
        <managed-bean-class>com.planit.smsrenta.controladores.AdministradorBean</managed-bean-class>    
        <managed-bean-scope>view</managed-bean-scope>
    </managed-bean>
    <managed-bean>
        <managed-bean-name>mercadoBean</managed-bean-name>
        <managed-bean-class>com.planit.smsrenta.controladores.MercadoBean</managed-bean-class>    
        <managed-bean-scope>view</managed-bean-scope>
    </managed-bean>
    <managed-bean>
        <managed-bean-name>categoriasServiciosBean</managed-bean-name>
        <managed-bean-class>com.planit.smsrenta.controladores.CategoriasServiciosBean</managed-bean-class>    
        <managed-bean-scope>view</managed-bean-scope>
    </managed-bean>
    <managed-bean>
        <managed-bean-name>departamentoBean</managed-bean-name>
        <managed-bean-class>com.planit.smsrenta.controladores.DepartamentoBean</managed-bean-class>    
        <managed-bean-scope>view</managed-bean-scope>
    </managed-bean>
    <managed-bean>
        <managed-bean-name>tipoLugarBean</managed-bean-name>
        <managed-bean-class>com.planit.smsrenta.controladores.TipoLugarBean</managed-bean-class>    
        <managed-bean-scope>view</managed-bean-scope>
    </managed-bean>
    <managed-bean>
        <managed-bean-name>facturaBean</managed-bean-name>
        <managed-bean-class>com.planit.smsrenta.controladores.FacturaBean</managed-bean-class>    
        <managed-bean-scope>view</managed-bean-scope>
    </managed-bean>
    <managed-bean>
        <managed-bean-name>colorBean</managed-bean-name>
        <managed-bean-class>com.planit.smsrenta.controladores.ColorBean</managed-bean-class>    
        <managed-bean-scope>view</managed-bean-scope>
    </managed-bean>
    <managed-bean>
        <managed-bean-name>nacionalidadBean</managed-bean-name>
        <managed-bean-class>com.planit.smsrenta.controladores.NacionalidadBean</managed-bean-class>    
        <managed-bean-scope>view</managed-bean-scope>
    </managed-bean>     
    <managed-bean>
        <managed-bean-name>sesionBean</managed-bean-name>
        <managed-bean-class>com.planit.smsrenta.controladores.SesionBean</managed-bean-class>    
        <managed-bean-scope>request</managed-bean-scope>
    </managed-bean>
    <managed-bean>
        <managed-bean-name>sesionActivaBean</managed-bean-name>
        <managed-bean-class>com.planit.smsrenta.controladores.SesionActivaBean</managed-bean-class>    
        <managed-bean-scope>session</managed-bean-scope>
    </managed-bean>
    <managed-bean>
        <managed-bean-name>tipoDuracionBean</managed-bean-name>
        <managed-bean-class>com.planit.smsrenta.controladores.TipoDuracionBean</managed-bean-class>
        <managed-bean-scope>view</managed-bean-scope>
    </managed-bean>
    <managed-bean>
        <managed-bean-name>localidadBean</managed-bean-name>
        <managed-bean-class>com.planit.smsrenta.controladores.LocalidadBean</managed-bean-class>
        <managed-bean-scope>view</managed-bean-scope>
    </managed-bean>
    <managed-bean>
        <managed-bean-name>parametroReservacionBean</managed-bean-name>
        <managed-bean-class>com.planit.smsrenta.controladores.ParametrosReservacionBean</managed-bean-class>    
        <managed-bean-scope>view</managed-bean-scope>
    </managed-bean>
    <managed-bean>
        <managed-bean-name>documentoBean</managed-bean-name>
        <managed-bean-class>com.planit.smsrenta.controladores.DocumentoBean</managed-bean-class>
        <managed-bean-scope>view</managed-bean-scope>
    </managed-bean>
    <managed-bean>
        <managed-bean-name>correoBean</managed-bean-name>
        <managed-bean-class>com.planit.smsrenta.controladores.CorreoBean</managed-bean-class>
        <managed-bean-scope>view</managed-bean-scope>
    </managed-bean>
    
    <navigation-rule>
        <from-view-id>*</from-view-id>
        
        <navigation-case>
            <from-outcome>Login</from-outcome>
            <to-view-id>/login.xhtml</to-view-id>
            <redirect/>
        </navigation-case>             
                       
        <!-- ADMIN PRINCIPAL -->
        <navigation-case>
            <from-outcome>AdminPDashboard</from-outcome>
            <to-view-id>/vistas/AdminP/general/PDashboard.xhtml</to-view-id>
            <redirect/>            
        </navigation-case>
        <navigation-case>
            <from-outcome>AdminPEditarPerfil</from-outcome>
            <to-view-id>/vistas/AdminP/general/PPanelEditarPerfil.xhtml</to-view-id>
            <redirect/>
        </navigation-case>
        <navigation-case>
            <from-outcome>AdminPFacturacion</from-outcome>
            <to-view-id>/vistas/AdminP/facturacion/PFacturacion.xhtml</to-view-id>
            <redirect/>
        </navigation-case>
        <navigation-case>
            <from-outcome>AdminPInformacionPersonal</from-outcome>
            <to-view-id>/vistas/AdminP/general/PInformacionPersonal.xhtml</to-view-id>
            <redirect/>
        </navigation-case>
        <navigation-case>
            <from-outcome>AdminPInformacionSesion</from-outcome>
            <to-view-id>/vistas/AdminP/general/PInformacionSesion.xhtml</to-view-id>
            <redirect/>
        </navigation-case>  
        <navigation-case>
            <from-outcome>AdminPVistaReserva</from-outcome>
            <to-view-id>/vistas/AdminP/general/PVistaReserva.xhtml</to-view-id> 
            <redirect/>       
        </navigation-case>
        <navigation-case>
            <from-outcome>AdminPPanelAdministracion</from-outcome>
            <to-view-id>/vistas/AdminP/administracion/PPanelAdministracion.xhtml</to-view-id>
            <redirect/>
        </navigation-case> 
        <navigation-case>
            <from-outcome>AdminPUsuarios</from-outcome>
            <to-view-id>/vistas/AdminP/usuarios/PUsuarios.xhtml</to-view-id>
            <redirect/>            
        </navigation-case>        
        <navigation-case>
            <from-outcome>AdminPClientes</from-outcome>
            <to-view-id>/vistas/AdminP/clientes/PClientes.xhtml</to-view-id>
            <redirect/>            
        </navigation-case>      
        <navigation-case>
            <from-outcome>AdminPCiudades</from-outcome>
            <to-view-id>/vistas/AdminP/ciudad/PCiudades.xhtml</to-view-id>
            <redirect/>
        </navigation-case>
        <navigation-case>
            <from-outcome>AdminPCategorias</from-outcome>
            <to-view-id>/vistas/AdminP/categorias/PCategorias.xhtml</to-view-id>
            <redirect/>            
        </navigation-case>
        <navigation-case>
            <from-outcome>AdminPEmpleados</from-outcome>
            <to-view-id>/vistas/AdminP/empleados/PEmpleados.xhtml</to-view-id>
            <redirect/>            
        </navigation-case>        
        <navigation-case>
            <from-outcome>AdminPEstadisticas</from-outcome>
            <to-view-id>/vistas/AdminP/estadisticas/PEstadisticas.xhtml</to-view-id>
            <redirect/>            
        </navigation-case>            
        <navigation-case>
            <from-outcome>AdminPPaises</from-outcome>
            <to-view-id>/vistas/AdminP/pais/PPaises.xhtml</to-view-id>
            <redirect/>            
        </navigation-case>
        <navigation-case>
            <from-outcome>AdminPMarcas</from-outcome>
            <to-view-id>/vistas/AdminP/marcas/PMarcas.xhtml</to-view-id>
            <redirect/>            
        </navigation-case>
        <navigation-case>
            <from-outcome>AdminPProveedores</from-outcome>
            <to-view-id>/vistas/AdminP/proveedores/PProveedores.xhtml</to-view-id>
            <redirect/>            
        </navigation-case>
        <navigation-case>
            <from-outcome>AdminPReferencias</from-outcome>
            <to-view-id>/vistas/AdminP/referencias/PReferencias.xhtml</to-view-id>
            <redirect/>            
        </navigation-case>
        <navigation-case>
            <from-outcome>AdminPTiposServicios</from-outcome>
            <to-view-id>/vistas/AdminP/reservas/PTiposServicios.xhtml</to-view-id>
            <redirect/>            
        </navigation-case>
        <navigation-case>
            <from-outcome>AdminPRoles</from-outcome>
            <to-view-id>/vistas/AdminP/roles/PRoles.xhtml</to-view-id>
            <redirect/>            
        </navigation-case>
        <navigation-case>
            <from-outcome>AdminPServicios</from-outcome>
            <to-view-id>/vistas/AdminP/servicios/PServicios.xhtml</to-view-id>
            <redirect/>            
        </navigation-case>
        <navigation-case>
            <from-outcome>AdminPVehiculos</from-outcome>
            <to-view-id>/vistas/AdminP/vehiculos/PVehiculos.xhtml</to-view-id>
            <redirect/>            
        </navigation-case>             
        <navigation-case>
            <from-outcome>AdminPCostosServicios</from-outcome>
            <to-view-id>/vistas/AdminP/servicios/PCostosServicios.xhtml</to-view-id>
            <redirect/>
        </navigation-case>
        <navigation-case>
            <from-outcome>AdminPLugares</from-outcome>
            <to-view-id>/vistas/AdminP/lugares/PLugares.xhtml</to-view-id>
            <redirect/>
        </navigation-case>
        <navigation-case>
            <from-outcome>AdminPDepartamentos</from-outcome>
            <to-view-id>/vistas/AdminP/departamentos/PDepartamentos.xhtml</to-view-id>
            <redirect/>
        </navigation-case>                 
        <navigation-case>
            <from-outcome>AdminPPanelCalificaciones</from-outcome>
            <to-view-id>/vistas/AdminP/calificaciones/PPanelCalificaciones.xhtml</to-view-id>
            <redirect/>
        </navigation-case>
        <navigation-case>
            <from-outcome>AdminPListaCalificaciones</from-outcome>
            <to-view-id>/vistas/AdminP/calificaciones/PListaCalificaciones.xhtml</to-view-id>
            <redirect/>
        </navigation-case>
        <navigation-case>
            <from-outcome>AdminPMercados</from-outcome>
            <to-view-id>/vistas/AdminP/mercados/PMercados.xhtml</to-view-id>
            <redirect/>
        </navigation-case>               
        <navigation-case>
            <from-outcome>AdminPReservaciones</from-outcome>
            <to-view-id>/vistas/AdminP/reservas/PReservaciones.xhtml</to-view-id>
            <redirect/>
        </navigation-case>
        <navigation-case>
            <from-outcome>AdminPCategoriasServicios</from-outcome>
            <to-view-id>/vistas/AdminP/servicios/PCategoriasServicios.xhtml</to-view-id>
            <redirect/>
        </navigation-case>        
        <navigation-case>
            <from-outcome>AdminPAsociarVehiculosServicios</from-outcome>
            <to-view-id>/vistas/AdminP/vehiculos/PAdminVehiculosServicios.xhtml</to-view-id>
            <redirect/>
        </navigation-case>
        <navigation-case>
            <from-outcome>AdminPAsociarVehiculosConductores</from-outcome>
            <to-view-id>/vistas/AdminP/vehiculos/PAdminVehiculosConductores.xhtml</to-view-id>
            <redirect/>
        </navigation-case>
        <navigation-case>
            <from-outcome>AdminPIrListaReservaciones</from-outcome>
            <to-view-id>/vistas/AdminP/reservas/PListaReservaciones.xhtml</to-view-id>
            <redirect/>
        </navigation-case>    
        <navigation-case>
            <from-outcome>AdminPParametrosReservaciones</from-outcome>
            <to-view-id>/vistas/AdminP/reservas/PAdministrarParametrosReservacion.xhtml</to-view-id>
            <redirect/>
        </navigation-case>  
        <navigation-case>
            <from-outcome>AdminPDocumentos</from-outcome>
            <to-view-id>/vistas/AdminP/facturacion/PDocumentos.xhtml</to-view-id>
            <redirect/>
        </navigation-case>
        <navigation-case>
            <from-outcome>AdminPCorreos</from-outcome>
            <to-view-id>/vistas/AdminP/administracion/PPanelCorreos.xhtml</to-view-id>
            <redirect/>
        </navigation-case>                               
      
        <!-- ADMIN SECUNDARIO -->
        <navigation-case>
            <from-outcome>AdminSDashboard</from-outcome>
            <to-view-id>/vistas/AdminS/general/SDashboard.xhtml</to-view-id>
            <redirect/>
        </navigation-case>
        <navigation-case>
            <from-outcome>AdminSPanelEditarPerfil</from-outcome>
            <to-view-id>/vistas/AdminS/general/SPanelEditarPerfil.xhtml</to-view-id>
            <redirect/>            
        </navigation-case>
        <navigation-case>
            <from-outcome>AdminSInformacionPersonal</from-outcome>
            <to-view-id>/vistas/AdminS/general/SInformacionPersonal.xhtml</to-view-id>
            <redirect/>
        </navigation-case>
        <navigation-case>
            <from-outcome>AdminSInformacionSesion</from-outcome>
            <to-view-id>/vistas/AdminS/general/SInformacionSesion.xhtml</to-view-id>
            <redirect/>
        </navigation-case>
        <navigation-case>
            <from-outcome>AdminSVistaReserva</from-outcome>
            <to-view-id>/vistas/AdminS/general/SVistaReserva.xhtml</to-view-id>                
            <redirect/>       
        </navigation-case>
        <navigation-case>
            <from-outcome>AdminSPanelAdministracion</from-outcome>
            <to-view-id>/vistas/AdminS/administracion/SPanelAdministracion.xhtml</to-view-id>
            <redirect/>
        </navigation-case>     
        <navigation-case>
            <from-outcome>AdminSCategorias</from-outcome>
            <to-view-id>/vistas/AdminS/categorias/SCategorias.xhtml</to-view-id>
            <redirect/>
        </navigation-case>
        <navigation-case>
            <from-outcome>AdminSCiudades</from-outcome>
            <to-view-id>/vistas/AdminS/ciudad/SCiudades.xhtml</to-view-id>
            <redirect/>
        </navigation-case>
        <navigation-case>
            <from-outcome>AdminSClientes</from-outcome>
            <to-view-id>/vistas/AdminS/clientes/SClientes.xhtml</to-view-id>
            <redirect/>
        </navigation-case>
        <navigation-case>
            <from-outcome>AdminSEmpleados</from-outcome>
            <to-view-id>/vistas/AdminS/empleados/SEmpleados.xhtml</to-view-id>
            <redirect/>
        </navigation-case>        
        <navigation-case>
            <from-outcome>AdminSPaises</from-outcome>
            <to-view-id>/vistas/AdminS/pais/SPaises.xhtml</to-view-id>
            <redirect/>
        </navigation-case>
        <navigation-case>
            <from-outcome>AdminSReferencias</from-outcome>
            <to-view-id>/vistas/AdminS/referencias/SReferencias.xhtml</to-view-id>
            <redirect/>
        </navigation-case>
        <navigation-case>
            <from-outcome>AdminSVehiculos</from-outcome>
            <to-view-id>/vistas/AdminS/vehiculos/SVehiculos.xhtml</to-view-id>
            <redirect/>
        </navigation-case>        
        <navigation-case>
            <from-outcome>AdminSMarcas</from-outcome>
            <to-view-id>/vistas/AdminS/marcas/SMarcas.xhtml</to-view-id>
            <redirect/>
        </navigation-case>
        <navigation-case>
            <from-outcome>AdminSReservaciones</from-outcome>
            <to-view-id>/vistas/AdminS/reservas/SReservaciones.xhtml</to-view-id>
            <redirect/>
        </navigation-case>
        <navigation-case>
            <from-outcome>AdminSTiposServicios</from-outcome>
            <to-view-id>/vistas/AdminS/reservas/STiposServicios.xhtml</to-view-id>
            <redirect/>
        </navigation-case>
        <navigation-case>
            <from-outcome>AdminSProveedores</from-outcome>
            <to-view-id>/vistas/AdminS/proveedores/SProveedores.xhtml</to-view-id>
            <redirect/>
        </navigation-case>  
        <navigation-case>
            <from-outcome>AdminSServicios</from-outcome>
            <to-view-id>/vistas/AdminS/servicios/SServicios.xhtml</to-view-id>
            <redirect/>
        </navigation-case>
        <navigation-case>
            <from-outcome>AdminSRoles</from-outcome>
            <to-view-id>/vistas/AdminS/roles/SRoles.xhtml</to-view-id>
            <redirect/>
        </navigation-case>
        <navigation-case>
            <from-outcome>AdminSAdministradores</from-outcome>
            <to-view-id>/vistas/AdminS/usuarios/SUsuarios.xhtml</to-view-id>
            <redirect/>
        </navigation-case>
        <navigation-case>
            <from-outcome>AdminSCostosServicios</from-outcome>
            <to-view-id>/vistas/AdminS/servicios/SCostosServicios.xhtml</to-view-id>
            <redirect/>
        </navigation-case>
        <navigation-case>
            <from-outcome>AdminSLugares</from-outcome>
            <to-view-id>/vistas/AdminS/lugares/SLugares.xhtml</to-view-id>
            <redirect/>
        </navigation-case>
        <navigation-case>
            <from-outcome>AdminSDepartamentos</from-outcome>
            <to-view-id>/vistas/AdminS/departamentos/SDepartamentos.xhtml</to-view-id>
            <redirect/>
        </navigation-case>
        <navigation-case>
            <from-outcome>AdminSMercados</from-outcome>
            <to-view-id>/vistas/AdminS/mercados/SMercados.xhtml</to-view-id>
            <redirect/>
        </navigation-case>    
        <navigation-case>
            <from-outcome>AdminSCategoriasServicios</from-outcome>
            <to-view-id>/vistas/AdminS/servicios/SCategoriasServicios.xhtml</to-view-id>
            <redirect/>
        </navigation-case>   
        <navigation-case>
            <from-outcome>AdminSParametrosReservaciones</from-outcome>
            <to-view-id>/vistas/AdminS/reservas/SAdministrarParametrosReservaciones.xhtml</to-view-id>
            <redirect/>
        </navigation-case>
        <navigation-case>
            <from-outcome>AdminSListaCalificaciones</from-outcome>
            <to-view-id>/vistas/AdminS/calificaciones/SListaCalificaciones.xhtml</to-view-id>
            <redirect/>
        </navigation-case>
        <navigation-case>
            <from-outcome>AdminSPanelCalificaciones</from-outcome>
            <to-view-id>/vistas/AdminS/calificaciones/SPanelCalificaciones.xhtml</to-view-id>
            <redirect/>
        </navigation-case>
        <navigation-case>
            <from-outcome>AdminSAsociarVehiculosConductores</from-outcome>
            <to-view-id>/vistas/AdminS/vehiculos/SAdminVehiculosConductores.xhtml</to-view-id>
            <redirect/>
        </navigation-case>
        <navigation-case>
            <from-outcome>AdminSAsociarVehiculosServicios</from-outcome>
            <to-view-id>/vistas/AdminS/vehiculos/SAdminVehiculosServicios.xhtml</to-view-id>
            <redirect/>
        </navigation-case>   
        <navigation-case>
            <from-outcome>AdminSIrListaReservaciones</from-outcome>
            <to-view-id>/vistas/AdminS/reservas/SListaReservaciones.xhtml</to-view-id>
            <redirect/>
        </navigation-case>       
        <!-- ADMIN SECUNDARIO -->
        
        <!-- CONDUCTOR -->
        <navigation-case>
            <from-outcome>ConductorDashboard</from-outcome>
            <to-view-id>/vistas/Conductor/general/CoDashboard.xhtml</to-view-id>
            <redirect/>
        </navigation-case>
        <navigation-case>
            <from-outcome>ConductorEdicionPerfil</from-outcome>
            <to-view-id>/vistas/Conductor/general/CoPanelEditarPerfil.xhtml</to-view-id>
            <redirect/>            
        </navigation-case>
        <navigation-case>
            <from-outcome>ConductorVistaReserva</from-outcome>
            <to-view-id>/vistas/Conductor/general/CoVistaReserva.xhtml</to-view-id>  
            <redirect/>          
        </navigation-case>
        <navigation-case>
            <from-outcome>ConductorInformacionPersonal</from-outcome>
            <to-view-id>/vistas/Conductor/general/CoInformacionPersonal.xhtml</to-view-id>
            <redirect/>
        </navigation-case>        
        <navigation-case>
            <from-outcome>ConductorInformacionSesion</from-outcome>
            <to-view-id>/vistas/Conductor/general/CoInformacionSesion.xhtml</to-view-id>
            <redirect/>
        </navigation-case> 
        <navigation-case>
            <from-outcome>ConductorListaClientes</from-outcome>
            <to-view-id>/vistas/Conductor/clientes/CoClientes.xhtml</to-view-id>
            <redirect/>
        </navigation-case>            
        <navigation-case>
            <from-outcome>ConductorIrListaReservaciones</from-outcome>
            <to-view-id>/vistas/Conductor/reservas/CoListaReservaciones.xhtml</to-view-id>
            <redirect/>
        </navigation-case>       
        <!-- CONDUCTOR -->
        <!-- Proveedor -->
        <navigation-case>
            <from-outcome>ProveedorDashboard</from-outcome>
            <to-view-id>/vistas/Proveedor/general/PrDashboard.xhtml</to-view-id>
            <redirect/>
        </navigation-case>
        <navigation-case>
            <from-outcome>ProveedorEdicionPerfil</from-outcome>
            <to-view-id>/vistas/Proveedor/general/PrPanelEditarPerfil.xhtml</to-view-id>
            <redirect/>            
        </navigation-case>  
        <navigation-case>
            <from-outcome>ProveedorEstadoVehiculos</from-outcome>
            <to-view-id>/vistas/Proveedor/vehiculos/PrEstadoVehiculos.xhtml</to-view-id>
            <redirect/>
        </navigation-case>
              
        <!-- Proveedor -->
               
        <!-- CLIENTE -->
        <navigation-case>
            <from-outcome>ClienteDashboard</from-outcome>
            <to-view-id>/vistas/Cliente/general/CDashboard.xhtml</to-view-id>
            <redirect/>
        </navigation-case>       
        <navigation-case>
            <from-outcome>ClienteEdicionPerfil</from-outcome>
            <to-view-id>/vistas/Cliente/general/CPanelEditarPerfil.xhtml</to-view-id>
            <redirect/>           
        </navigation-case>  
        <navigation-case>
            <from-outcome>ClienteVistaReserva</from-outcome>
            <to-view-id>/vistas/Cliente/general/CVistaReserva.xhtml</to-view-id>
            <redirect/>     
        </navigation-case>
        <navigation-case>
            <from-outcome>ClienteInformacionSesion</from-outcome>
            <to-view-id>/vistas/Cliente/general/CInformacionSesion.xhtml</to-view-id>
            <redirect/>
        </navigation-case>
        <navigation-case>
            <from-outcome>ClienteInformacionPersonal</from-outcome>
            <to-view-id>/vistas/Cliente/general/CInformacionPersonal.xhtml</to-view-id>
            <redirect/>
        </navigation-case>
        <navigation-case>
            <from-outcome>ClienteReservaciones</from-outcome>
            <to-view-id>/vistas/Cliente/reservas/CReservaciones.xhtml</to-view-id>
            <redirect/>
        </navigation-case>      
        <navigation-case>
            <from-outcome>ClienteListaReservaciones</from-outcome>
            <to-view-id>/vistas/Cliente/reservas/CListaReservaciones.xhtml</to-view-id>
            <redirect/>
        </navigation-case>
        <navigation-case>
            <from-outcome>ClienteTiposServicios</from-outcome>
            <to-view-id>/vistas/Cliente/reservas/CTiposServicios.xhtml</to-view-id>
            <redirect/>
        </navigation-case>
        <navigation-case>
            <from-outcome>ClienteCalificarReservaciones</from-outcome>
            <to-view-id>/vistas/Cliente/reservas/CCalificarReservaciones.xhtml</to-view-id>
            <redirect/>
        </navigation-case> 
        <!-- CLIENTE -->       
    </navigation-rule>
                 
                       
    
    <navigation-rule>
        <from-view-id>/login.xhtml</from-view-id>
        <navigation-case>
            <from-outcome>Register</from-outcome>
            <to-view-id>/register.xhtml</to-view-id>
            <redirect/>
        </navigation-case>
        <navigation-case>
            <from-outcome>OlvideContrasena</from-outcome>
            <to-view-id>/olvideContrasena.xhtml</to-view-id>
            <redirect/>                  
        </navigation-case>
    </navigation-rule>
    <navigation-rule>
        <from-view-id>/register.xhtml</from-view-id>
        <navigation-case>
            <from-outcome>Login</from-outcome>
            <to-view-id>/login.xhtml</to-view-id>
            <redirect/>
        </navigation-case>
    </navigation-rule> 
    
         
    <!--Retornos en reservacion-->     
    <navigation-rule>
        <from-view-id>/vistas/AdminP/reservas/PReservaciones.xhtml</from-view-id>
        <navigation-case>
            <from-outcome>RegresarAdminPReservacion</from-outcome>
            <to-view-id>/vistas/AdminP/reservas/PReservaciones.xhtml</to-view-id>
        </navigation-case>
    </navigation-rule>
    <navigation-rule>
        <from-view-id>/vistas/Cliente/reservas/CReservaciones.xhtml</from-view-id>
        <navigation-case>
            <from-outcome>RegresarClienteReservacion</from-outcome>
            <to-view-id>/vistas/Cliente/reservas/CReservaciones.xhtml</to-view-id>
        </navigation-case>
    </navigation-rule>
    <navigation-rule>
        <from-view-id>/vistas/AdminS/reservas/SReservaciones.xhtml</from-view-id>
        <navigation-case>
            <from-outcome>RegresarAdminSReservacion</from-outcome>
            <to-view-id>/vistas/AdminS/reservas/SReservaciones.xhtml</to-view-id>
        </navigation-case>
    </navigation-rule>
    
</faces-config>
